nina_advanced_mcp.py
iflow_mcp_nina_advanced_api_mcp-0.1.0.dist-info/METADATA
iflow_mcp_nina_advanced_api_mcp-0.1.0.dist-info/WHEEL
iflow_mcp_nina_advanced_api_mcp-0.1.0.dist-info/entry_points.txt
iflow_mcp_nina_advanced_api_mcp-0.1.0.dist-info/top_level.txt
iflow_mcp_nina_advanced_api_mcp-0.1.0.dist-info/RECORD
