Metadata-Version: 2.4
Name: iflow-mcp_nina_advanced_api_mcp
Version: 0.1.0
Summary: Model Context Provider for N.I.N.A. astrophotography software using Advanced API
Author-email: IFLOW <iflow@example.com>
License: MIT
Project-URL: Homepage, https://github.com/PaDev1/Nina_advanced_api_mcp
Project-URL: Repository, https://github.com/iflow-mcp/nina_advanced_api_mcp
Project-URL: Issues, https://github.com/PaDev1/Nina_advanced_api_mcp/issues
Classifier: Development Status :: 4 - Beta
Classifier: Intended Audience :: Developers
Classifier: License :: OSI Approved :: MIT License
Classifier: Programming Language :: Python :: 3
Classifier: Programming Language :: Python :: 3.8
Classifier: Programming Language :: Python :: 3.9
Classifier: Programming Language :: Python :: 3.10
Classifier: Programming Language :: Python :: 3.11
Classifier: Programming Language :: Python :: 3.12
Requires-Python: >=3.8
Requires-Dist: fastmcp>=0.1.0
Requires-Dist: fastapi>=0.95.0
Requires-Dist: uvicorn>=0.22.0
Requires-Dist: pydantic>=2.0.0
Requires-Dist: aiohttp>=3.8.0
Requires-Dist: python-dotenv>=1.0.0
Requires-Dist: python-dateutil>=2.8.2
Requires-Dist: pytz>=2023.3
Requires-Dist: structlog>=23.1.0
Requires-Dist: typing-extensions>=4.5.0
